{
    "users": {
        "374183950": "修修猫ww",
        "13630870": "草莓味陳总",
        "24490897": "粉红奇子",
        "12561989": "秋雪Cyuki",
        "355685636": "-碎冰冰w",
        "35715213": "-KUYO-",
        "3546916627417611": "厌蠢症qwq",
        "636049479": "萧萧兮夜",
        "27802387": "高山老幾",
        "3546664497318540": "小兔乖乖QwQ",
        "3546645207714142": "蛋宝大人",
        "15716109": "一口猫毛子",
        "327958279": "花泽香兔",
        "596624087": "竹竹竹竹竹-take",
        "58222051": "苍帝-鸢尾",
        "642400757": "姜鱼Jiang_a",
        "693252150": "呙呙ovo",
        "3546712979278752": "发发發財_",
        "673947670": "是什么鸽子",
        "1148976599": "啾啾啾这呀",
        "3493280704629265": "爱在希雅前_",
        "3546971891566950": "H_浪",
        "3546654617635099": "小圆Rabi",
        "3546918011537829": "若若不男Z",
        "220204920": "发发儿-_-",
        "515941645": "余温wwi",
        "3546930095327491": "若有偌",
        "456081437": "不可一世茹宝",
        "3546817992067225": "晴一夏夏",
        "382224187": "Anlin_临",
        "363683789": "茶涧三沫",
        "3546786377501413": "吉一大人",
        "1878673": "生产队的毛病马",
        "6794797": "122大王",
        "1136087954": "软月月-疯狂减脂版",
        "3546608526428241": "波比大王の",
        "3537124806625531": "-养只软软软-",
        "10822451": "吃颗星星-",
        "3632299717429628": "bili_3632299717429628",
        "36187475": "居居boom",
        "388265493": "落羽-百万粉还不到",
        "403357469": "白柠喵Mew",
        "1804813716": "鱼丸排骨煲",
        "16709790": "软糖丸籽",
        "1811660": "雯粥粥i",
        "67072384": "只吃甜头吖",
        "52602303": "HanariSama",
        "3546593429031651": "泠的美少女日记",
        "12730372": "凝酱koru",
        "438512188": "灰宝儿honster",
        "435599873": "月亮hoshi",
        "1679640088": "六六小阿姨是我",
        "49832802": "双吉堡堡好吃捏",
        "313171": "阿証証証証",
        "7577631": "凉子rioko",
        "1084908938": "蓝藻细胞",
        "3546900143803207": "比利比利最懂你的人",
        "630548636": "雨萝nia",
        "3546978298366575": "舒豆豆豆",
        "646112650": "阿巴阿巴儿",
        "349113664": "幼安因因",
        "499412113": "晟晟晟晟涵",
        "20460312": "小昆仑仑",
        "271533050": "阿喵喵Yoki",
        "3546983887276760": "舞鉴盯帧",
        "6548616": "爆肝狂魔汐兔子",
        "478481279": "渠河river",
        "545203194": "樱花妹猎手Official",
        "2331228": "圆滚滚的小H",
        "3546937580063414": "丽芙_LIV",
        "3493135575419361": "英俊的芋头",
        "3493119010015607": "每日观赏",
        "1840839347": "舒舒爱睡觉禁止盗图",
        "89428420": "只想大口干饭ovo",
        "336301513": "YouTube中国视频",
        "1120177822": "九影视剪辑",
        "2350559": "菌烨tako",
        "2837929": "小南宫zzZ",
        "324862340": "苏沐棠-",
        "1954922550": "皮皮猫pipi-",
        "1695079716": "草莓味安安",
        "476835418": "台妹大调查",
        "3461575182649354": "脸脸板",
        "12503169": "瑾曦曦曦_",
        "1239292392": "甜妹区",
        "2077271908": "女丑女丑是妞妞",
        "3494372452600074": "-猫禾子",
        "2073801516": "言言抱枕",
        "696663255": "喂喂是小付呀",
        "3546880940182014": "甜心宝贝Sweetie",
        "17335495": "戏命猫あ",
        "161952273": "baobao_821",
        "3546655875926225": "奶芙心里软i",
        "22138604": "猫猫大人的日记",
        "1509390286": "奶白奶白de兔叽",
        "17604687": "黑小依",
        "15107703": "新纯chun_",
        "3546621247752895": "雪球不是雪球球",
        "3546972990474347": "栗子吃栗栗",
        "1132402902": "栀訫沁",
        "3546778553027049": "灰宝耶耶",
        "36327680": "yanyan_oxo",
        "1699279338": "白羊不白wy",
        "690426371": "鱼板面面ovo",
        "1395053138": "呆呆萱大王",
        "886992": "炭烧奶蛋",
        "24445248": "麻辣烤兔子a",
        "3546914236664268": "熟睡无能的丈夫",
        "607847878": "一块姜姜-",
        "2415337": "谁吃橘子不剥皮啊",
        "439058956": "清竹不是竹清",
        "3546971763641206": "二次元鉴赏家i",
        "391901062": "遇见初夏-",
        "432129912": "川奈の祥子",
        "1913854082": "西木子kuri_",
        "228767870": "一枚短腿彼岸嗷",
        "3493077213776788": "蒜蒜喝水",
        "3546883056208442": "空台戏月",
        "107709277": "派派饼w",
        "3546847582882293": "云锦锦锦锦喵",
        "85735196": "窨砚_Frasto",
        "544130591": "大妲己-swich微坦版",
        "3493256935507971": "甜欲由乃",
        "170227634": "祈雪ivy",
        "367262849": "一里ouo",
        "19670879": "无颜小天使",
        "510981977": "车美艳charmys",
        "504984820": "D海底鲸",
        "95768450": "玖玖儿c",
        "3546827651549409": "-玥玥好困-",
        "3546687012342391": "都听小菲的",
        "3546853849172195": "jocygs",
        "3546960816507358": "大乖乖G",
        "471379": "魔法猫猫王迟迟",
        "382960506": "功夫小宝贝",
        "3461577600665697": "紫菜蛋花吖",
        "365654312": "浅九ninth",
        "3546940180531748": "呆幽u",
        "3494358733031979": "橘小狗_",
        "508745646": "鸭鸭鸭琲",
        "48477621": "长安九月人微凉",
        "3537110499854585": "亿杯希米露-",
        "376057527": "兔牙Sinar酱",
        "3546937055775240": "Yasal_170",
        "1341422210": "傻猪凡_努力更新版",
        "1327719714": "BELLA贝拉F",
        "3493138589026513": "果汁水蜜桃_抗冻版",
        "1410463135": "澹台璟翎",
        "547909553": "CosPiano",
        "4999314": "团子烧肉",
        "637187407": "o橘Mua",
        "3546684051164024": "九只鸦鸦鸦",
        "3546595578612595": "你被竺拱了",
        "8806760": "香草喵露露",
        "51205452": "铁锅炖圆神",
        "1610732518": "Yulili莉莉子",
        "111530704": "加零爱吃猪脚饭",
        "386653291": "DunderMifflinHR",
        "401012029": "影潮千",
        "231780990": "すべてのバカ",
        "312816850": "雉鸣minz",
        "486732969": "伤心小蛋ovo",
        "7527048": "哔崽ovo",
        "353693094": "记不住露",
        "410606408": "甜宠Tino",
        "742354": "颜玖喵仙女",
        "1572584394": "明星鉴赏局",
        "3546851634580241": "Kiki梨大王",
        "6791307": "书玉枝",
        "386460499": "摄影师姚佳俊",
        "238171819": "陈忠祥",
        "3493276483062373": "Aurora-遇儿",
        "250620366": "LENivayaAya_爱雅",
        "268973566": "兔叽学妹",
        "390185140": "藻睡藻起好嘛好的",
        "1552320680": "小古kiddo",
        "3546834362436023": "誰吃橘子不剥皮啊",
        "582306": "诺成功",
        "23739456": "烦恼小小贝",
        "3546713870568181": "日常养眼",
        "2028029610": "水乐姐",
        "3546374557665913": "Yuna洁",
        "3493140224805325": "Borusushi狩司司",
        "1352662788": "湖里狸里狸",
        "13574291": "阿抽崽",
        "512421363": "胡椒饿了_Mi",
        "3546899434965149": "空巢小豚宝-破碎版",
        "3546843204028906": "超元小软肉",
        "3546912571525403": "手抖得像KC",
        "3546573988432614": "牢幽大王",
        "8572852": "墨玉-M",
        "1878578": "遥山药药",
        "3403527": "蒋七七ChiChan",
        "1141240027": "优拉Yola",
        "16548749": "冉冉不甜v",
        "14672053": "稀有材料33",
        "432045988": "邰鹤Tsuru",
        "3546733168561041": "-忧郁的U-",
        "322649079": "春野游記一",
        "8361911": "宾哔哔",
        "495689781": "苏酥yuki",
        "490558635": "一盆大蒜",
        "3466903": "香草奶喵",
        "3546712226401081": "佑米UMe",
        "686354330": "淘气雪蕊",
        "457910329": "你的闪儿",
        "319031647": "无敌橙橙橙仔",
        "2173008": "紫氯氯",
        "177355221": "鸠大王sama",
        "1635923": "简言啦噜噜噜噜噜",
        "9278223": "小奶童babedoll",
        "3546571132111646": "Yiko湿润兔",
        "3494356935772619": "崇义五",
        "697290208": "西园寺Sakura",
        "39349549": "月一吖",
        "390631574": "BOLOLI_SHOP",
        "274982872": "Ulrich-橘楠枳",
        "11151787": "可达鸭与花花牛仔",
        "3546896505244362": "蓉宝来这边了呢",
        "3546913303432065": "菜菜大王333",
        "443196209": "YY的日常报备鸭",
        "533996453": "王筱沫沫丶",
        "93876791": "魔王大人Maou",
        "513523736": "脆皮duck",
        "86648129": "刘兴兴ovo",
        "14079121": "玵木_Anmua-",
        "40389544": "殷洛洛ovo",
        "596837523": "飞宰吃瓜",
        "179288789": "汤面桢子",
        "241241850": "忱狸O3O",
        "3537108222347306": "颜值区",
        "2130126982": "荔枝小桃",
        "1237830462": "害羞的鲻鱼啊",
        "5978570": "-二二二月",
        "171368594": "六二二同学w",
        "1302451349": "小正义teioku",
        "387385097": "小以南超超超Q",
        "3015651": "镜酱_",
        "7014232": "吖静sizu222",
        "22840678": "喵呐喵喵喵",
        "1780216667": "绅士俱乐部A",
        "399858228": "飞吻vivien",
        "1445832997": "扶桑栖霞",
        "3546700713035996": "奈白老师-体力版",
        "576899": "w百合欧皇子ww",
        "25701856": "-烧鸡翼",
        "3546644360465346": "阿沫大大大",
        "8155759": "幺鸡w",
        "607871322": "果酱波波茶",
        "121075": "瓜希酱",
        "3493289888057574": "祭理yoyo",
        "447249555": "伤心猫-R雨",
        "508217482": "晓宇儿Rainy",
        "3494377934555297": "小妲己o",
        "3546571257940827": "抓喵喵喵",
        "3493279152736345": "知之要摘月",
        "28442677": "小北芽子",
        "24454064": "吃了个迟x",
        "20812175": "一只大蓝莓",
        "5617437": "天才少女Yuki",
        "44927348": "美羊羊の",
        "282038905": "合女",
        "15211712": "小箱子鸭",
        "1887943000": "且试茶茶",
        "378970197": "清清日常无语",
        "3493293037979816": "一条悠米Y",
        "3494366832232497": "美味橘子酱",
        "413957": "染墨初白",
        "1308126": "嶋葵",
        "2083636409": "安小菲akane",
        "3546575827635037": "奶瓶-kuomii",
        "81595107": "小小天艺",
        "3546682524437273": "幸運Max",
        "382485850": "圣枪嘉然",
        "1823872": "逆光R",
        "5899772": "吉萌_",
        "5914361": "阿璇学妹",
        "3546753852770566": "淼淼老湿",
        "488178291": "小野莉乃",
        "247999404": "乌苏苏-",
        "512394614": "七蛇蛇蛇",
        "3075365": "箜月Tsuki",
        "3546715407780810": "司玥儿",
        "1845381": "几兔灰",
        "99050024": "鸦九儿",
        "3546638610073782": "干饭小鹿鹿",
        "11605312": "青鸢Cyan-",
        "3546578738481796": "NO0YING",
        "1643978": "真夏zwei",
        "3546574051347256": "胖胖不胖Ui",
        "3546842197395745": "ktyoy",
        "524154749": "Kwj洛灵宝贝",
        "8590300": "李诽尘",
        "384903084": "-天夫人-",
        "413184623": "柒大姨",
        "355924716": "娜娜neo阿姆斯特朗",
        "8581342": "菌子宝宝丶",
        "6415681": "才不是木木",
        "20912836": "Misamisaaa_a",
        "3546378508699711": "余瑾年-",
        "13647660": "竹笙Zoe",
        "505311709": "小芋喵_以梦冠",
        "3546761438169591": "鸢鸢有点甜",
        "2349443": "伊小兔yuiko",
        "154103904": "小狐丨",
        "1708611203": "冷气大魔王",
        "354962346": "小奶糕Milky",
        "1574624": "糕哥枣糕DAZE",
        "493766774": "施梦露",
        "1383020261": "小香狗子",
        "7798663": "椿卷梦游中",
        "15183062": "巫小萤",
        "49676": "阿呆每天都不想动",
        "3546901651655172": "小怡爱宅",
        "4096581": "病院坂saki",
        "46792903": "Sachikowo",
        "382162544": "小溪Liz",
        "1909121890": "阿九儿baby",
        "3546733365692939": "好好吃的水饺",
        "3546758156126654": "不怕辣的熊熊酱",
        "9161587": "伊喵_Master",
        "6784676": "小清晨儿_",
        "691605376": "哇哦大牛牛",
        "504468324": "FairaStar_法拉",
        "15385187": "兔总裁s",
        "1396363458": "木子的生活小店",
        "2154169": "神祈祈",
        "3494380809750611": "孟程程_",
        "3546385559324700": "小颜眠眠",
        "1605904595": "六六侦探事务所",
        "645789964": "小鹤owo",
        "436948269": "九鸟Dolores_",
        "19221607": "绮玥Jul",
        "8874302": "豌豆粉er_",
        "3546378571614602": "殷韵韵",
        "514471213": "柒忆QIYI",
        "5008191": "琉璃青RO沉迷runa酱",
        "38874226": "修桃崽汁",
        "3546378636626044": "贾斯汀比汀",
        "9293142": "宫本樱樱酱",
        "673507076": "绫雪rteKn",
        "1366664945": "兔兔吃点啥",
        "7574854": "是栾栾啊_",
        "1236045494": "小野寺Z鱼",
        "2228831": "呆毛窝",
        "585302676": "王牌双娇",
        "3546574368016518": "乌珑珑",
        "383677806": "大蒜杀君",
        "308690042": "Tanuki狸猫喵",
        "4479943": "-梓貓-",
        "1280289656": "橘kikuko",
        "3546786278935055": "镜树树",
        "1173935238": "粤次元",
        "3546890528360872": "魅魔006",
        "1723164693": "兔兔和雷雷",
        "237748526": "爱跳舞的周清欢",
        "3546868766214892": "菟饱0v0",
        "1064663434": "Dz小小尼",
        "669270855": "摇滚小狼aowuaowu",
        "431458606": "湮湮ovo",
        "1232724631": "花颜悦目坊",
        "3546890469640443": "小晕崽の圈",
        "3546753842284627": "星梨梨S",
        "539595077": "小兔日记1212",
        "305353485": "男人的精神粮食",
        "3546664526678102": "奶酪的香味",
        "5759478": "无敌利群",
        "493682377": "芋泥啵耶",
        "20580358": "酸奶酸奶__",
        "108877022": "Angus厚牛堡-",
        "131758407": "椰子茶茶茶茶",
        "476407215": "爱吃芒果v",
        "3546803018401836": "观韵使者",
        "3493273152784750": "一条小糖糖",
        "481450341": "-月楼Uro-",
        "39065623": "吃八口奶酪-",
        "301230394": "小泽又沐风0v0",
        "6844293": "雾奈哟",
        "3536997073291285": "彩虹胡桃",
        "276191534": "是可乐要加冰",
        "18354629": "言忆iya",
        "17367640": "尸菌菌qwq",
        "1090115346": "杂鱼川川",
        "382894360": "庭树沐年",
        "3493114532596159": "清的小跟班",
        "279866": "千葉球球",
        "248402269": "池鱼要摸鱼",
        "3904677": "雨乃哟",
        "650870468": "大G卡戴珊angel",
        "438664702": "睡仙糖糖",
        "3546885744757526": "魁魔355",
        "2010776822": "干饭瞳瞳子",
        "6189069": "小糖发财",
        "696365080": "不再煜煜",
        "212955": "兔子烧owo",
        "8446999": "王未来什么都行",
        "1736504999": "努力的张嘎嘎",
        "20110522": "佚柔姐姐0102",
        "1505452997": "招财小卡卡",
        "1323218982": "芋圆有点甜-",
        "353214559": "anykissa",
        "3546851007531322": "白白CC睡个好觉",
        "1905878": "铁板欧尼酱",
        "96123053": "花见团子喵",
        "3546877022702042": "梦梦Miao_",
        "2011822166": "爱迟到的张锦锦",
        "3546850416134790": "E御老师",
        "491455061": "-小满意-",
        "3546840400137058": "Doll乖",
        "3493288730429676": "虚无虚爱",
        "535117700": "与姬子",
        "392102108": "别抢点点电视",
        "3494378131687428": "赵小七呢",
        "1774842423": "younggoal羊羔",
        "3546579285838502": "欢乐跳跳兔",
        "395375056": "中国梨自救",
        "3461576162020182": "Nnmo_",
        "3546662484052067": "娃娃卡哇伊捏",
        "46356715": "吉子一一",
        "848008": "-MyMy麦麦-",
        "96795170": "关于小忆",
        "486607999": "七七脸不圆",
        "81715210": "仙九Airi",
        "3493283441412923": "三星小凛",
        "258957570": "超级小禾儿",
        "3546606076955208": "我的璐璐吖ovo",
        "442319830": "国风小迷妹",
        "3546668723079416": "啵奇塔o",
        "411182763": "抱抱念酱",
        "3546639113390569": "茹茹老板",
        "386943950": "努力的十八魔",
        "383668230": "是辞妹o",
        "388052154": "我系小羊_",
        "3546694320917120": "叙小沐mua",
        "1548774513": "爱看欧美片的bro",
        "2047657077": "浣熊统领",
        "521621734": "你心动了莓",
        "179187121": "Kyuu久久",
        "12678866": "零零凛凛",
        "356631272": "ぃ福运满载ヾ",
        "26604229": "千千好运爆棚",
        "3546869716224009": "舞蹈小娜",
        "3546789965728059": "小小痣学姐",
        "2064968489": "颜妲己er",
        "1709911562": "TendergingeR",
        "3546702327842855": "小也sama_",
        "673001225": "金毛地鼠",
        "1598128093": "小小德下士",
        "3546745017469598": "一抹晨曦b_b",
        "175928": "水饺",
        "477535791": "时姬娘娘_",
        "3546678625831066": "刘晓小O0oo",
        "6353313": "铁铁元",
        "12219431": "一只吱吱子",
        "23362672": "妤丸呐",
        "1417418115": "叁叁得啾啾",
        "26287758": "鱼子酱不能睡懒觉",
        "487695781": "一番星baby",
        "38205779": "智呀个智障",
        "323594686": "bili_323594686",
        "513843658": "拿拿Suna",
        "287540377": "莹宝也是宝",
        "657817": "如月灰",
        "438276052": "派拉PO",
        "490967418": "牙牙籽",
        "432487901": "真迹无疑",
        "1598306351": "林杏仁Almond",
        "1804041153": "咩咩黑化版",
        "356010767": "走路摇ZLY",
        "2095524736": "Sjrun汲润_桃子",
        "3546704198502518": "猫不理包崽",
        "675844791": "喵喵球球丶",
        "3546578159667556": "登登凹凹凸凸",
        "95672339": "小番茄果酱",
        "105799582": "御喵さま",
        "342229730": "祈春-库存发不完了版",
        "2077986216": "小三金呀_",
        "535271748": "-你说森莫",
        "3690996437093026": "肥肥的朋友圈",
        "1729330578": "月芽儿uuo",
        "3546823769720844": "果咩那塞果果",
        "4876980": "小祭漓-gili",
        "3546812298299855": "M桃花匠l",
        "4378669": "一色雨",
        "246598195": "萌桃moe",
        "1538452479": "旺仔牛奶QQ塘",
        "670032046": "小羊咩咩baa",
        "477013288": "小小付日记",
        "31240684": "橘系fairy",
        "3690971644561496": "cosplay鉴赏家",
        "35686685": "C゙",
        "7144444": "盐太ovo",
        "471305903": "水目小土",
        "37478976": "审美强化",
        "1237293261": "小海豹美美",
        "3546974133422485": "利齐Leezy",
        "3632320187730300": "你的瑄瑄呀",
        "1434821599": "九曲-jean",
        "476656953": "菠萝喵桑",
        "3546856499973057": "呦呦不吃佑佑",
        "3546384565274965": "海盐甜菠萝",
        "3537124286532397": "欧阳277",
        "281094236": "柃江不是杠铃",
        "1046612968": "小胖优选",
        "186682178": "铃鹿山鱼丸",
        "9893405": "达菲鸡呀",
        "3632287740594909": "禾节节",
        "8315419": "小沫不是萌汉子吖",
        "39237954": "tgm741096071",
        "17134597": "珮珮不是呸呸w",
        "438924960": "德洛斯Delous",
        "3546920423262343": "大雄的小院",
        "3690971208354546": "是多多多多多多多",
        "499830801": "猴皮筋仙人",
        "291853913": "atmm543",
        "3546955812702595": "成都执法大队",
        "1238714495": "憨憨露露q",
        "778073": "KK好饿",
        "3546557840362268": "李缥青",
        "90909": "天迫恋星",
        "3546790817171944": "肥肥得吃正能量",
        "3546641764190976": "兔子兔几兔耳朵",
        "3632311383886199": "依雅哟masane",
        "11619612": "蜜汁猫裘",
        "3632318101064314": "酒儿cc",
        "393161858": "樱竹西",
        "16168590": "Koa1a想睡觉",
        "1452969877": "韩大師",
        "1323971495": "TwoY歪歪",
        "26154312": "小缘酱nya",
        "472311": "Fumika病叶",
        "3546947365374715": "饺饺叽",
        "507475067": "三月潜",
        "3546973395224595": "认证MILF-Hunter",
        "214391420": "KeyKeyKiYoMi",
        "1985852883": "音羽美奈Mina",
        "324446457": "小野寺YI",
        "95940546": "木木是好木",
        "470210448": "一颗小梨子哎",
        "3546611869288838": "月亮hoshi的第二人格",
        "1979206917": "浅凝半夏Oo",
        "3537123426699273": "一颗熊子",
        "527597232": "比基尼沙滩的章鱼哥",
        "3546937299045025": "洛小雨oni",
        "3493126662523507": "波波熊真好吃",
        "358045660": "一口忆酱",
        "33646906": "冥冥不困zzz",
        "37974722": "小椰猫猫椰",
        "638658753": "赵可欣hhh",
        "9922021": "五尺多桃酥",
        "288639670": "36d的大美女",
        "18353095": "虫虫爱摸鱼",
        "2114425949": "刷到算你号养成",
        "9956879": "宝藏美女",
        "3546842553911356": "-Miua-",
        "89239646": "Alan卓玛",
        "439258602": "甜黑o",
        "3546974229891237": "Min-米妮",
        "3546716548631335": "环球_视野",
        "1385358434": "白话搬运工",
        "29248907": "是你的小葵葵",
        "2021818669": "骨牙路子野",
        "11360156": "小邪神飛踢Official",
        "3546982217943969": "链接视界",
        "661185325": "北北不北北qwq",
        "3546860092393722": "粥舟人As",
        "3546956622203578": "宝宝酱_a-",
        "692144743": "67岁异域舞娘",
        "1980903042": "破碎小瑾ya",
        "3493137838246283": "UP主有好痴的1",
        "3546901263681972": "苏酥-SASM",
        "3546831107656191": "米饭炒蒜苔",
        "3493080747477361": "黑羊嘿嘿",
        "5659436": "阿槿努力不熬夜",
        "44582229": "苍苍子__",
        "3546876578106169": "椰椰小芒果",
        "3546575001356360": "熬夜小王子-旭公子",
        "3546942395124389": "小宋的女装真美",
        "33873499": "冷风吹过的夏天",
        "225518446": "汪汪脆脆桃",
        "3746949": "圆脸馨儿",
        "26261068": "_糖果果Candy_",
        "437119941": "卡比酱Ww",
        "1318110277": "就是卷卷呀i",
        "382889882": "爆炒咕咕鸡",
        "3461579569892099": "阿斯忒芮雪",
        "689259784": "maki酱の日常",
        "3546783833655752": "肥姐宝宝",
        "1550178577": "东樱奈",
        "39709960": "喵子NIEKO",
        "34467204": "嗲嗲酱哦",
        "8162377": "seya-狮砸",
        "359": "Machi马吉",
        "523682710": "-时分秒-",
        "1766152": "Cchua华仔",
        "274763540": "再吃一口希尔",
        "3546893737003964": "阳光的郭奉孝",
        "486487299": "雪夜yer",
        "2506239": "风筝筝筝w",
        "33934828": "淳兮兮兮喵",
        "3367958": "昼貓hiru",
        "32906278": "絮宝与玫瑰",
        "3546964954188624": "agakong小花生",
        "52604693": "晴晴拌饭-",
        "697360195": "樱铃春岛",
        "3546907320257090": "安楠又楠",
        "384192042": "圆脸的灰灰",
        "1133433799": "赏尽风花雪月",
        "3493262805437197": "小兔糕toto",
        "1627957": "最白的幽一",
        "1502995166": "财神六一路",
        "27215501": "喵星人要占领地球",
        "396428065": "糕糕不吃糖-",
        "3546954367764736": "Godseolhwa",
        "3546607068908380": "大猪猪猪-",
        "27810096": "阈限漫游者",
        "450618568": "珂珂汤小圆",
        "3546956513151373": "陆许y",
        "9123984": "傲娇怪比",
        "1098171699": "の查理",
        "111194070": "御菟QAQ",
        "697688041": "来点奶酪",
        "12948629": "樱落Selena_",
        "3546906730957203": "蠢药_",
        "275230721": "郝饱饱饿了",
        "6677483": "狐裂裂",
        "3546557844556377": "Monster-骸骨钢",
        "1600801600": "落寞奈萝",
        "3546776220994202": "雪非雪花",
        "11551288": "兔哥w",
        "3546867539380827": "小娜米-",
        "1084715223": "忧郁の涵酱",
        "11427800": "过期米线线喵",
        "176447020": "苒苒不想打咩了",
        "287043924": "狂风之刄",
        "3546818950465857": "AutoSonyeo",
        "3461572997417576": "范真学姐",
        "663321": "焖焖碳-",
        "71024696": "是小猫崽子耶",
        "3546650201032945": "沈筱晗w",
        "1389787828": "诺米团崽",
        "3546916780509830": "Suu盐酥酥",
        "386655047": "大风吹啊啊啊哇哇哇",
        "3546915786459359": "芙芙大人耶",
        "476309254": "喵呜橙",
        "3546941398976855": "UK耶耶",
        "13807642": "小圆脸鹿鹿",
        "403529079": "武陵寺",
        "43900362": "B站治愈馆主",
        "15076745": "彩虹酱哇",
        "32496357": "L林酒J",
        "384290186": "一道寒芒抖了几下",
        "3546860383897845": "超絶可愛いnamika酱",
        "1431996375": "是离宝",
        "593394363": "猫猫3岁-",
        "2045302616": "小呆妹Doll",
        "3546927836694833": "元教教主",
        "643663223": "Momoko葵葵",
        "587011962": "小尤渴了",
        "3546816631016023": "大家好叫我睫毛",
        "677265289": "橙子味的奶油雪塔_",
        "39856370": "七城Lawrence",
        "314532476": "小喵缇子",
        "692806969": "波克比心_",
        "3493114369018215": "菠萝拌饭u",
        "22459049": "摇光_yzy",
        "3546593531792072": "Aurora-尕尕",
        "480182655": "烨云月桂",
        "3546391221635562": "南歌mikkan-",
        "3546848428034910": "去码头整点薯条KK",
        "3546938211305491": "beatberry314",
        "233269767": "闪耀溪溪",
        "20206082": "我也是读春秋的",
        "26480472": "改个名字单推鹿乃",
        "3494357246150781": "狗伍伍wu",
        "1812364": "夏神SuliiX",
        "16322326": "丝言不吃包子",
        "204208844": "黎骦",
        "3461562874464391": "-果冻橙子-",
        "3546788187342877": "凉飕飕zip",
        "630484698": "呱呱大帝_",
        "519763002": "小兔吱QUQ",
        "3546901236418723": "包包汁ye",
        "3546890972957197": "小熊堡堡捏",
        "3546914901461612": "茶啤啤koi",
        "3546965937752340": "麻心汤圆吖",
        "3690991842232843": "外面鬼混回来了",
        "3546382369557318": "孙圆圆2号线",
        "17437888": "宵鱼鱼",
        "29457406": "阿昭Akira",
        "74473661": "雪糕_popsicle",
        "2851020": "_糖小V_",
        "3546638433913274": "成都水妹加油努力",
        "350744607": "苏苏Suda吖",
        "3546868346784598": "小水滴哒滴",
        "509069409": "幼蓝蓝",
        "3951904": "贰加六",
        "3546970945751097": "美七七ssss",
        "26177922": "小须须_Arcana",
        "640567930": "Ahri小狐狸呀",
        "1570781689": "瑶瑶同学sama",
        "529891599": "大大卷卷小卷",
        "3690982220499740": "宝贝请留步",
        "3632308735183120": "Yuli优优",
        "836885": "清和Alicia",
        "1003029369": "琳琳吃不饱_-",
        "3690980477766570": "美七七女王",
        "2122895527": "张小丸丸子cc",
        "2456543": "帆仔oink",
        "3493258388834940": "哈基咪ov0",
        "30791360": "你壮哥_",
        "62539429": "矢绫静奈",
        "1481675": "流一",
        "3546867826690052": "糖豆abby",
        "3546959187020549": "小夜猫老师",
        "1842405816": "董花苗苗DM",
        "1419558215": "入我镜剧社",
        "3546971291781882": "小苏酱好困",
        "538748264": "bili_538748264",
        "1589558174": "Sjrun汲润丝袜",
        "3546937322113185": "nariddyangKR",
        "3546642282187746": "貅貓謎伢",
        "1334711": "丧男PALADIN",
        "3493266760665661": "晚橘夏晚风",
        "3632318824582082": "小瓜子秽土转生版",
        "1991934510": "满月风铃",
        "432919124": "执念sss_",
        "11473818": "岚西啊喵",
        "476861689": "钙片老师回归版",
        "2137805243": "卡比兽sptemer",
        "687659265": "麦克斯的荒野建造领域",
        "2087675075": "甜煮沃野",
        "2084434964": "我忒麦伦",
        "492342038": "-萧萧气",
        "8447574": "窝窝奶兔",
        "691240431": "奶糯kk",
        "91136837": "花兮_honoka",
        "3493266615962052": "大美女小彤",
        "454984558": "抖个姬灵",
        "3546897276996466": "AC喵喵君",
        "13346799": "七毒喵",
        "3546980728965600": "YouTuBe每日大赛1",
        "3546983929219906": "米米mi讷",
        "410727121": "水原小可",
        "1284184786": "眠羊妹妹m",
        "10893225": "草莓粥粥爱吃肉",
        "1357590138": "yuuhui玉汇",
        "3546903050455980": "KaCi脆脆",
        "19702611": "汐尔sama",
        "12356652": "傻喵叫哈猫儿",
        "3493277087042285": "玉er小宝贝",
        "1610218623": "野生小佳宝",
        "3493145270552925": "我金克丝超厉害",
        "25887651": "若影轻风",
        "3461579527948676": "张德彪ik",
        "3546958954236605": "姥姥姨姨夫夫",
        "3546795074390733": "花间格物",
        "1477074": "菌儿rikushi",
        "3493291819535155": "-黄大侠La",
        "3494362602277029": "zzzzz小鱼zzz",
        "3314672": "yui金鱼",
        "86431266": "泽鸽啊",
        "409793037": "-阿猫_",
        "393627115": "l永l生",
        "500828653": "羽生三未",
        "3546860224514263": "爱练臀的小公主",
        "110852933": "以墨ink-",
        "1024339854": "我真不吃土豆y",
        "3546911961254108": "废雾女大",
        "3546735018248999": "崽崽不吃青菜yy",
        "65890998": "五更百鬼",
        "1393074963": "Lady鹿的ootd",
        "3461578053651308": "蕾诺诺Rina_",
        "233962606": "屑度子",
        "351007224": "肉肉团Barry",
        "108595231": "老猫爱偷腥",
        "282019708": "大钟宝",
        "110357281": "欲E咪咪",
        "480289895": "嬭㐃",
        "3546969727306482": "小猫坏事做尽-体力版",
        "425812": "叉烧熊仔包",
        "34792981": "带恶人啊伟",
        "3546973909026835": "盐稚u理",
        "489131636": "灵魂的颜色_",
        "698270800": "RH懒羊羊大王",
        "489852501": "星野理理ovo",
        "1990549330": "弃奶从武",
        "1124726847": "星璐-official",
        "1938319625": "巧莓冰70",
        "392358853": "好南捏_",
        "21660287": "沐头大王",
        "407432743": "邪恶蛋黄酱酱",
        "290696159": "_小小夭_",
        "443049558": "可爱的阿cui",
        "276187015": "笠崽",
        "647160948": "身体乳学姐",
        "3546960925559002": "ovo呀嘞呀嘞啊",
        "3690988096719704": "AAA滔神",
        "8414821": "薄荷绿绿子",
        "3690972135295961": "奶粉学姐",
        "1005779939": "雅音酱Masane",
        "1904141992": "秋雾风爱猫",
        "2783878": "夏紫嫣",
        "563193419": "aihmh",
        "1733859618": "姜姜几",
        "11080586": "Oo蛋獭舒芙蕾oO",
        "15998945": "你的狂野饼干",
        "3690981884954752": "纸鸢samo-以か之名冠",
        "215905774": "Stellaluna018",
        "3546394442861262": "小鸡不好惹ooo",
        "516088962": "李丹妮丶",
        "3690978005223681": "小晓Z-",
        "24443956": "柠檬san",
        "3493120440272914": "猫猫大人的b站",
        "1108411264": "jcklenhd",
        "12123574": "桃酱爱吃火锅",
        "40903042": "一只奶俏",
        "503492188": "汤圆四水",
        "3632307848088470": "颜控私藏馆",
        "3632302353549451": "牢分享官重生版",
        "317032378": "Kop-小鹿",
        "51001994": "付以蕊",
        "3461575163775413": "掘宝大师",
        "381188279": "橙几要睡大觉",
        "582971054": "骨茶酱_q",
        "3546804645792127": "Kou悠悠",
        "3546900997343610": "柔柔-sub",
        "365964766": "風花ましろ",
        "90087521": "厚礼蟹谢谢",
        "296900402": "奶瑶妹妹",
        "205254711": "大灯爱好者",
        "8598025": "图图堡",
        "3690970614860229": "熈菥",
        "3537105078717056": "小嫩御",
        "3493143376824520": "芥末鱼板板板",
        "3632303142078678": "78岁纯情老婆",
        "1443290793": "奶昔达酱喵",
        "329197062": "社恐双马尾丶RT",
        "381833538": "ins美女馆",
        "3546666854517440": "大白兔D胡萝卜",
        "3546660269459716": "萌宅-日更版",
        "73415842": "香老师123",
        "3546632790477121": "爱活特AiHot",
        "1565005058": "猫蓝北是裁缝",
        "505252200": "白白巧克李",
        "325844": "Biu_杜冥鸦",
        "339873612": "桃姬不咕咕",
        "694021925": "酒制土豆_",
        "1295285638": "魔杖大户",
        "14870218": "谢锦竹",
        "475262443": "温温小秃头",
        "523165888": "憨堡堡o",
        "1285185116": "一杯桑葚汁",
        "471474481": "舒芙蕾su",
        "17168001": "仓大佬",
        "1308677060": "小香菇w",
        "12974242": "香菇堡w",
        "3493133646039953": "椒兔",
        "668536305": "小玉FuF",
        "3546375841122891": "写不来MATH_",
        "1178432681": "婉琳hajime_",
        "3546931798214955": "77睡不着Ouo",
        "3493140537281097": "莓莓嗷-",
        "3546933708720526": "瓜瓜快起床",
        "430712299": "一只修鸟w",
        "89308291": "打完这把喂猪_",
        "2147776": "红豆豆z",
        "1222351264": "清许___",
        "1283558672": "野源娜的日常",
        "160366489": "咕咕顾言一",
        "43802337": "唐老猫呀",
        "3546751432657335": "婉O呐",
        "3546857854733055": "猫几o0",
        "8048877": "Midoriko绿子",
        "1471508": "柠好不好",
        "2070286097": "天梨昭昭",
        "455511061": "-町枝-",
        "1883021017": "Lov佑佑",
        "405741497": "aunt_steph_",
        "1600113": "萌爱moi",
        "3546941600303804": "兽米香香香",
        "15092277": "阿七不太御",
        "3493260743936120": "林小鱼yyds",
        "20067185": "十元酱少女",
        "1319421855": "桂花酒酿香",
        "2321397": "小拿铁ouo",
        "3546641084713858": "梨轩呀",
        "629718380": "啊然早起犯困版",
        "179557079": "不二丸叽",
        "364088332": "小玟不是小玫",
        "14935491": "小狗杀鱼",
        "22693918": "imisabelll",
        "156211": "樱梨梨Eriri",
        "355903877": "抱走布丁-",
        "86694518": "呆滞芋圆丶",
        "2009929": "咝小喵MAO",
        "3546908125563416": "小鱼77s",
        "1302614305": "Lisa辰",
        "3546824677787939": "Vecchio_",
        "580341": "奶油Kuriimu",
        "14810274": "那个桃子C",
        "586968469": "女神是高圆圆1",
        "3493261985450277": "仙女厅",
        "498099165": "一颗小兔娘",
        "3494358099692362": "雪柔睡不醒",
        "4889986": "是团宝吖",
        "1821673278": "绝世蘑菇",
        "493538731": "三月是风",
        "19936565": "宫本绘",
        "13410681": "来点宫酱w",
        "3546672940452569": "__好运_",
        "3546558758914330": "意小满-鸿运版",
        "3546758005132177": "徐可乐o",
        "356512412": "呆呆娜娜子",
        "504859080": "樱酱又在说单口相声",
        "3546855317179161": "iuv可乐",
        "3690976260393451": "小琪大王-OuO",
        "3546707226790807": "森川梨生奈",
        "3690994623056373": "高圆圆-a",
        "1450407934": "超社恐的美乐蒂v",
        "3494377942944418": "坏线虫www",
        "1792388968": "开机ll",
        "22276848": "饿酱OuO",
        "3546827093707407": "QQ鱼_",
        "3546767895300962": "瑜诗诗要暴富",
        "3493288497646038": "小美老师d",
        "26636751": "媛媛上青山",
        "3546381270649659": "李又一",
        "3546717272148376": "呆呆小苒-",
        "3493131160913998": "鱼鱼一只",
        "1176071036": "盐汁尤梨yuri",
        "3546647252437088": "小栩小不点-",
        "44569248": "小虞姬Owo",
        "3546614809496140": "欣欣King_",
        "3546964771735986": "元气芊芊子",
        "3546609145088997": "灌注大白菜",
        "2088998338": "爱笑的小羽_",
        "407414188": "真香KK",
        "3546649370561283": "枳月味奶片",
        "3546919020267557": "我萌晕晕噜",
        "510990477": "Ameme咩咩",
        "3546926062504823": "白笙笙iio--土豆冠",
        "3494368998590560": "沛沛碎碎念",
        "318386480": "林夏之-",
        "3546952809580772": "小小忄怡",
        "3546891432233251": "夏夏子以梦",
        "1646746": "菜崽",
        "3546562194049708": "霂木马",
        "3690972082866628": "心动露丝S",
        "522396102": "有点晕的呆呆酱",
        "25237642": "陈姜姜",
        "3546885094639843": "新月-EX",
        "1410853603": "小鹿漫漫y",
        "2094233792": "一只夏木啊丶",
        "3493083782056221": "余喵儿",
        "3546812453488878": "Yk-空降女友-招主持",
        "1158617144": "鱼粉雪琪",
        "406744713": "一只羊o1",
        "3546642257021274": "女明星甜甜",
        "261030084": "布丁今天生日o",
        "509120671": "豫见-303",
        "318284347": "楚楚baby_",
        "3632302336772364": "LX-004",
        "14682911": "活捉一只丽",
        "16605529": "miriちゃん",
        "449958577": "甜甜甜甜宝u",
        "3461562723470258": "Kitty不说嗨",
        "2863356": "树里酱Juri",
        "46498284": "菠菜小哭包",
        "1986329935": "婠婠_owo",
        "8347380": "叫初恋吧",
        "3546933530463191": "西海岸-梦幻7彩舞团",
        "107711217": "小鱼仔ouo-",
        "3546730232547959": "斯文姐姐呀",
        "1743572249": "小满_廿四",
        "1728137": "赤樱sakura",
        "872065": "一织小香猪",
        "353042505": "小可学妹_",
        "22627844": "花栗鼠大队长",
        "3632306317167074": "仙逆-踏云殿",
        "3494371081063173": "魚妹不熬夜",
        "3546730538732430": "聂老师_NN",
        "3546645958494307": "佐伊Z0E",
        "1073692608": "陪珊看云海",
        "7847261": "陆识衣和王严言",
        "603214947": "芯儿老婆",
        "478288846": "归墟cr-喵小乖的小狗版",
        "439062543": "不礼喵",
        "2131609593": "余多多Dudu",
        "3546944819431530": "代号不是007_",
        "558246120": "耶耶突-好运版",
        "662400144": "ziyi子意",
        "3690988767808187": "v麦当当v",
        "1625089549": "小凡在干嘛-冷漠版",
        "1682581": "神女士嘉嘉",
        "3546383762065466": "dy李晴雪",
        "3546627920890177": "2026对金安安好亿点",
        "381159823": "潇靳语就是命好",
        "3546943307384997": "AKA王刚",
        "3537117445622549": "吉米yomi",
        "1317059990": "野生小板栗-",
        "3546835010456413": "唐糖D",
        "144923856": "呀思思",
        "3690994797120218": "黛Dair",
        "76721667": "小日和啾",
        "598808891": "草莓果酱呐",
        "3494371601156566": "漫漫iiiii",
        "3546966225061989": "冒险岛-",
        "3546628803791133": "小梨儿宝贝",
        "3546607769357106": "荔奈-版",
        "1029040366": "猫猫小伞_21日生日满月",
        "3546791056247045": "冰糖雪狸_勤奋版",
        "3632299650320572": "软软熊zzZ",
        "43976851": "鹿也不知道",
        "540129519": "幺幺粼",
        "3546770002938006": "钦钦草原-",
        "397648078": "念月月_",
        "95135476": "艺柠煤气罐",
        "1487482": "钟意大堡包",
        "41322626": "特伦苏苏ss",
        "338735697": "安慕茜不喝酸奶",
        "434163904": "BlaC01不可",
        "3546812472363250": "圆宝圆宝_",
        "3493132272404811": "代代巡山",
        "11616487": "绝不早到小吱吱",
        "482969247": "思小柒Umi",
        "83742728": "中国舞两雨西子",
        "3546865096198355": "软软Yii",
        "5067153": "千昭不想变成千日召",
        "3546590132308924": "银河doki-",
        "3690987582917188": "优乐美-1月16满月啦",
        "3690976551897744": "爱意小姨-伊布冠",
        "3546933975058608": "梨枝雪-",
        "1524295896": "果-果奶",
        "3493266441898039": "稚稚妹妹",
        "1650038050": "喜多多-活命版",
        "625523418": "我叫D三一",
        "3546660525312099": "so嘟嘟辣",
        "3546955756079388": "我要爆辣-",
        "483420778": "小羽很不错",
        "3493272097917120": "绾绾会发光吖",
        "169555859": "小柚yuyu",
        "23730725": "小椰学姐",
        "1484230523": "西海岸HOT",
        "487474416": "一颗甜葡",
        "3690981698308791": "奶黄包u",
        "519491852": "春日部文文",
        "485942530": "诺宝-16号周年快乐",
        "3546924451891252": "牢小坨-余梦冠",
        "3546607578516439": "小蜗の日记_",
        "3546703594523131": "卿卿Shine",
        "2125012841": "甜欣学姐-",
        "3493258837625596": "电子咩咩酱",
        "25518113": "哎哟阿尤_",
        "3632304821897363": "喵叽小呆",
        "1384085547": "御宅小绵",
        "628424163": "小白好睡觉",
        "622642036": "九命猫不爱鱼",
        "3546824864434520": "oio小池抚月",
        "3546802674469763": "咬人小小兔-",
        "3493258082650786": "邪恶小飞棍-反差版",
        "8591769": "橙月儿大橙子",
        "1229504579": "哈基妍-",
        "12358533": "奶油蘑蘑汤",
        "3546914830158493": "在在Zayah",
        "3546984382204066": "u懒懒大王",
        "1796067519": "一碗梨梨冻呀-cc冠",
        "1607814206": "の兔宝m-缺守护",
        "3546840486120054": "小困包333",
        "3690980173678764": "AURORAX星晨组",
        "3493123216902885": "辣妹blueblood",
        "3546858580347598": "啃啃排骨",
        "3494370886027771": "啵啵梨o3o",
        "3546944498567681": "羊酱Aaa",
        "3546732289853493": "尤卡Yy",
        "3546750230989227": "悦悦puppy",
        "3546930722376042": "饼饼饱饱io",
        "3546880535431994": "泠泠池",
        "3546974406052271": "羊羊吃不饱-缺舰长版",
        "20479057": "困困蛋挞zzz",
        "2143844054": "Kamioioi",
        "409590942": "怂包岁",
        "3632305910319830": "馒头音in子",
        "1549538352": "艾诺宝_",
        "3546791593117936": "困眠眠o",
        "451012603": "Sue酥酥-15号生日版",
        "641988463": "孤单宝宝汐",
        "3546791949633798": "大橘子姐姐-体力版",
        "3690975727716698": "烧麦_体力版",
        "3690970686163002": "可乐-sister",
        "1301317469": "小巴_z",
        "13904372": "哼哼唧唧的懒锤锤",
        "3546883244951809": "诺诺kiss-想要幸福版",
        "3690986045704720": "鹿初姐姐",
        "1377180432": "吃不下了吖",
        "26882738": "多冰3分甜",
        "3546830279280814": "麦丽素有点甜呐",
        "3632305195190283": "天降小卷饼_",
        "1412753731": "迷糊在桃公主",
        "3632310807169258": "小燃燃rrr",
        "3546866799086389": "桃子-ya-",
        "388818302": "清清小晚晚",
        "514623980": "妖精七七i",
        "3546936703453826": "乐芙-努力版",
        "3546578027547073": "柚子小嘉",
        "663789404": "小知_15号半周年版",
        "3494368249907293": "小鹿圆Oo",
        "3546632819837595": "温暖_____",
        "33029911": "kim软软猫",
        "1758481522": "萝莉小囍",
        "3546860184668629": "er荔",
        "44800219": "wild稚一",
        "89124107": "E人凌雨晗",
        "3546575850702987": "洛汐lxe",
        "3546904042408147": "零零007-",
        "3546557337045787": "柚子茶齁甜_",
        "3632309272053932": "柚子小钱-",
        "3546911717984649": "蒲蒲ii",
        "3691000293755169": "小泽沐风又拂面",
        "2114021472": "小饱cookie-16号百天版",
        "3546920408582425": "淘桃e",
        "273264155": "雾理不是物理-",
        "3546941990373883": "糖醋虞子酱",
        "3546863881947588": "-琳木木",
        "3632306319263838": "水中月2026",
        "3632305241327856": "小渔仔崽_",
        "3546641399286286": "小哆酱酱",
        "3546381866240016": "小七iy",
        "2041758227": "汉堡包dudu",
        "3546930386831578": "XH萌力全开",
        "3546822008113727": "涂涂樾樾",
        "107610587": "Coral-133",
        "1819548520": "桃酥Momo",
        "3546616441080094": "孟言不闲",
        "3546892501781476": "绵酱o",
        "1695014312": "迟早早oi",
        "3546789349165215": "温u嫚漫",
        "3546857454176436": "拜见小怡大王z",
        "3546644329007272": "好椰oo",
        "1809273215": "小夜不会说话",
        "2505240": "爱之小魔仙",
        "3546886860442012": "Ok_BB",
        "3546958864058691": "k9小萝",
        "3546715334379596": "皮漾漾",
        "3546892520655491": "s-初恋派对",
        "3546825615215308": "困困酱-唱见连",
        "3546811830635381": "芭小娜-nana",
        "3546856323811450": "居居棒居居",
        "3690978640661334": "汝汝im",
        "3632310853306737": "希狗狗子-缺舰版",
        "3537117531605507": "阿欲16号满月版",
        "4696786": "柔柔Crystal_C",
        "3546869728807424": "一只眠羊-vo",
        "3546855105366518": "KoKo-唱见连",
        "3632307841797087": "小晚夕",
        "3546912072403284": "Miki妍大王",
        "3546742433778095": "荔枝na",
        "403043622": "果粒橙QvO",
        "82594762": "是晚晴也",
        "3493134539425925": "凌宝宝丶",
        "1588417299": "刚子歌-",
        "393707883": "不一般的球球",
        "1059246688": "茼酱Ovo",
        "1894830920": "不想睡觉的大福",
        "483898098": "是听听鸭_",
        "3690985332672540": "芋泥米啵啵-求好运版",
        "8278365": "Lucius_卢修斯",
        "3546596518136538": "肉爪坨坨",
        "3632311033661904": "莫醒宝宝",
        "507585202": "小luooooooo",
        "2002028563": "瑶师傅-",
        "3546977350453545": "小姨Yaa",
        "3691001793219285": "苍井诱m",
        "2070152605": "热可可q",
        "419077716": "丫猫西比",
        "10070015": "安歌_Ni",
        "1745222332": "宅妹小菜ye-好运版",
        "3546963878349310": "小茯酱",
        "3690970040241037": "NOVA-星核少女",
        "3632310253521692": "桃花江-009",
        "1894018616": "F-醒醒土豆宝",
        "3546925601130869": "A八尺大人-16号半周年",
        "1840249285": "-好运花生",
        "17510848": "咕嘟杳杳",
        "661438392": "你要找哪个小文",
        "316942846": "废宅三文鱼-1月21生日",
        "85729717": "Kiki向前冲呀",
        "3690982725913434": "聆乐Live-品质点唱",
        "516529612": "伊布恬",
        "3546904168237689": "啵啵原子o",
        "3546375841122361": "io六六酱",
        "3546983218285525": "热舞时代-星空001",
        "1990455546": "雅君不哑巴",
        "520841572": "SG-幻想物语",
        "158424918": "忽绾绾",
        "1210682371": "浮生楼",
        "3493265900833477": "静静大姐姐_好运版",
        "80741431": "一条CC_摸鱼版",
        "3460280": "巫春天",
        "3546805023279503": "在下毛毛鱼_",
        "551462934": "椰奶酱i",
        "3546940327332680": "小袁饼干YA",
        "3546923743054497": "西海岸-幻梦007",
        "3546624460589804": "碎叫叫-缺舰版",
        "3546937930287362": "熙颜咩",
        "1248480946": "慕儿YA",
        "3632307380423086": "小小毛豆nei",
        "3546924449794664": "XH蓉妹来临",
        "3546716531853344": "-CCO_o",
        "1697563889": "别说我吃的多",
        "3546928472132015": "SG酒馆",
        "3546768597846928": "安妮塔Oo",
        "1556573952": "我才不是普信女",
        "3690986702113458": "奶凶奶凶的F小姨",
        "3690999901587602": "娜美_S_",
        "3546595930934114": "妍的日记本",
        "3546965019200272": "天才阿瑶_",
        "151297494": "海苔脆-Andy冠-",
        "3546585036229249": "崽恩恩",
        "3546666418309800": "幸运的祺子",
        "147693277": "徐雾阳-",
        "3494380258200406": "木子欣欣欣oO8",
        "400681032": "沈清依_21号生日版",
        "3546830277183985": "小蜜疯_璀璨",
        "3546570517645916": "夏烟烟_",
        "400426072": "芝士小鱼饼饼",
        "35368646": "小夏不肥肥",
        "2065331875": "甜甜记不住",
        "1278510825": "早早龙",
        "3632319894128980": "伊吉神",
        "3546887049185571": "小沐睡不醒-缺舰版",
        "7370915": "羊咩羊羊羊",
        "3690975297800530": "可愛い漫",
        "3546775401007486": "苏-苏妲己",
        "90108118": "星梦语-",
        "238323057": "喵喵是只猫耶",
        "3546619203029689": "奶芙气泡U",
        "690252345": "M_芥末花生",
        "3546674926455444": "苏阮-16号满月",
        "3546970163513856": "妞妞大王o-o",
        "3546891117660347": "不叫陈好运",
        "3546827999677294": "WheneverIMiss",
        "1126287583": "3727222",
        "3690997682801384": "琦琦星冰乐哇哇",
        "3632315714505159": "yys老师",
        "3546642554816775": "曹葵葵i",
        "3690993022929239": "-念念酱_",
        "297137461": "超级木Aki",
        "3546958671120927": "小幸运-交友点唱-布丁",
        "3632303595063306": "一口一个小不点",
        "47834551": "炫一勺饭",
        "3546956689311853": "西红柿-小西洋洋版",
        "1799727551": "YT-芭比Girl",
        "250067078": "狐坨驾到",
        "44986936": "锦小梨ohh",
        "3546895991442068": "沐瑶一体力版",
        "3493256614644233": "布丁焦糖了",
        "1805523729": "意恩小宝贝",
        "3546964580895502": "暴妮熊",
        "3690980091890306": "GL-美少女",
        "3690994893588932": "jx-九万里",
        "3690975719328131": "星澜001",
        "647115800": "XL-喀什",
        "3546983362988424": "决战无限城123",
        "3632309068630418": "WX-盘丝洞",
        "3690977231374680": "Fire-魔仙堡",
        "266831439": "IG总裁办",
        "475299851": "绯色电影院",
        "3546969656002964": "2in1-火力少女",
        "3546952878787435": "翻斗花园女团",
        "3546956322310508": "甜心-101",
        "1041537349": "元气少女计划",
        "667758672": "YT--cat",
        "3690991351499566": "SeeU-喜柚",
        "1778251903": "0308渝你相见",
        "3546693396072557": "Queen-168",
        "3546889051965627": "巴厘岛女团-养猪厂",
        "1557866202": "拾光彩虹星球",
        "3632311432121169": "TB-G梦纱会",
        "3494365496346934": "香山-萌妹少女",
        "662977759": "绘梦-space",
        "3632316008106734": "星澜002",
        "3546866090248832": "LV-T1",
        "383670059": "香山-外滩001",
        "3546932857276592": "香山-少女季"
    }
}
